mqtt/__init__.py
mqtt/_version.py
mqtt/error.py
mqtt/pdu.py
mqtt/client/__init__.py
mqtt/client/base.py
mqtt/client/factory.py
mqtt/client/interfaces.py
mqtt/client/interval.py
mqtt/client/publisher.py
mqtt/client/pubsubs.py
mqtt/client/subscriber.py
mqtt/client/test/__init__.py
mqtt/client/test/test_base.py
mqtt/client/test/test_factory.py
mqtt/client/test/test_publisher.py
mqtt/client/test/test_pubsubs.py
mqtt/client/test/test_subscriber.py
mqtt/test/__init__.py
mqtt/test/test_pdu.py
twisted_mqtt-0.3.11.dist-info/LICENSE
twisted_mqtt-0.3.11.dist-info/METADATA
twisted_mqtt-0.3.11.dist-info/WHEEL
twisted_mqtt-0.3.11.dist-info/top_level.txt
twisted_mqtt-0.3.11.dist-info/RECORD
