Metadata-Version: 2.1
Name: twisted-mqtt
Version: 0.3.11
Summary: twisted-mqtt is a library using the Twisted framework and implementing the MQTT protocol (v3.1 & v3.1.1)
Author-email: Rafael González <rafael08@ucm.es>, Jaime Zamorano <jzamorano@fis.ucm.es>
License: MIT
Project-URL: Homepage, https://github.com/astrorafael/twisted-mqtt
Project-URL: Repository, https://github.com/astrorafael/twisted-mqtt.git
Classifier: Programming Language :: Python :: 3.9
Classifier: Programming Language :: Python :: 3.10
Classifier: Programming Language :: Python :: 3.11
Classifier: Programming Language :: Python :: 3.12
Classifier: Development Status :: 4 - Beta
Classifier: Environment :: Console
Classifier: Framework :: Twisted
Classifier: Topic :: Communications
Classifier: Topic :: Internet
Classifier: License :: OSI Approved :: MIT License
Classifier: Operating System :: POSIX :: Linux
Requires-Python: >=3.9
License-File: LICENSE
Requires-Dist: twisted
